./.gitignore
./LICENSE
./PKG-INFO
./README.md
./main.py
./pyproject.toml
./.idx/.gitignore
./.idx/dev.nix
./examples/hello_world.stax
./examples/math.stax
./stax/__init__.py
./stax/command_handler.py
./stax/stack.py
./stax/token.yml
staxlang-0.0.1.dist-info/METADATA
staxlang-0.0.1.dist-info/WHEEL
staxlang-0.0.1.dist-info/entry_points.txt
staxlang-0.0.1.dist-info/licenses/LICENSE
staxlang-0.0.1.dist-info/RECORD
