Metadata-Version: 2.1
Name: staxlang
Version: 0.0.1
Summary: A Stack-based ZISC-like interpreter written in Python
Project-URL: Homepage, https://github.com/try3d/staxlang
Project-URL: Bug Tracker, https://github.com/try3d/staxlang/issues
Author-email: Try3D <rsarans186@gmail.com>
License-File: LICENSE
Classifier: License :: OSI Approved :: MIT License
Classifier: Operating System :: OS Independent
Classifier: Programming Language :: Python :: 3
